arduino_exporter/__init__.py
arduino_exporter/cli.py
arduino_exporter/prometheus.py
arduino_exporter/serial.py
arduino_exporter/server.py
arduino_exporter/exception/__init__.py
arduino_exporter-0.8.15.dist-info/licenses/LICENSE.txt
arduino_exporter-0.8.15.dist-info/METADATA
arduino_exporter-0.8.15.dist-info/WHEEL
arduino_exporter-0.8.15.dist-info/entry_points.txt
arduino_exporter-0.8.15.dist-info/top_level.txt
arduino_exporter-0.8.15.dist-info/RECORD
