Metadata-Version: 2.4
Name: arduino_exporter
Version: 0.8.15
Summary: Arduino Prometheus Exporter.
Home-page: https://github.com/clivern/arduino_exporter/
Author: Clivern
Author-email: hello@clivern.com
License: MIT
Project-URL: Documentation, https://github.com/clivern/arduino_exporter/
Project-URL: Source, https://github.com/clivern/arduino_exporter/
Project-URL: Changelog, https://github.com/clivern/arduino_exporter/blob/main/CHANGELOG.rst
Project-URL: Tracker, https://github.com/clivern/arduino_exporter/issues
Project-URL: Download, https://pypi.org/project/arduino_exporter/#files
Platform: any
Classifier: Development Status :: 5 - Production/Stable
Classifier: Programming Language :: Python
Classifier: License :: OSI Approved :: MIT License
License-File: LICENSE.txt
Requires-Dist: click<=8.2.1
Requires-Dist: pyserial<=3.5
Requires-Dist: prometheus-client<=0.22.1
Requires-Dist: importlib-metadata<=8.7.0; python_version <= "3.11"
Dynamic: license-file
